publish_event_sns/__init__.py
publish_event_sns/publish.py
publish_event_sns-0.0.3.dist-info/LICENSE
publish_event_sns-0.0.3.dist-info/METADATA
publish_event_sns-0.0.3.dist-info/WHEEL
publish_event_sns-0.0.3.dist-info/top_level.txt
publish_event_sns-0.0.3.dist-info/RECORD
