Metadata-Version: 2.1
Name: publish-event-sns
Version: 0.0.3
Summary: Publish message into SNS Topic with attributes
Home-page: https://github.com/msantino/publish-event-sns
Author: Marcelo Santino
Author-email: eu@marcelosantino.com.br
License: UNKNOWN
Platform: UNKNOWN
Classifier: Programming Language :: Python :: 3
Classifier: License :: OSI Approved :: MIT License
Classifier: Operating System :: OS Independent
